{"files":{"src\\pages\\products\\column-config.vue":{"frameworks":["vue-router","vite-plugin-vue-devtools","vite-plugin-vue-layouts","unplugin-vue-router","unplugin-auto-import","unplugin-vue-components","@unocss/preset-icons","@vue/devtools","@pinegrow/vite-plugin","@vitejs/plugin-vue","vue","app_designer","project","pg.insight.events","pg.vue.tree.painter","pg.css.grid","pg.image.overlay","pg.code-validator","pg.project.items","pg.asset.manager","pg.html"]},"index.html":{"frameworks":["pg.insight.events","pg.vue.tree.painter","pg.css.grid","pg.image.overlay","pg.code-validator","pg.project.items","pg.asset.manager","pg.html"]},"src\\pages\\products\\products-list.vue":{"frameworks":["vue-router","vite-plugin-vue-devtools","vite-plugin-vue-layouts","unplugin-vue-router","unplugin-auto-import","unplugin-vue-components","@unocss/preset-icons","@vue/devtools","@pinegrow/vite-plugin","@vitejs/plugin-vue","vue","app_designer","project","pg.insight.events","pg.vue.tree.painter","pg.css.grid","pg.image.overlay","pg.code-validator","pg.project.items","pg.asset.manager","pg.html"]},"src\\App.vue":{"frameworks":["vue-router","pg.insight.events","pg.vue.tree.painter","vite-plugin-vue-devtools","pg.css.grid","pg.image.overlay","pg.code-validator","pg.project.items","vite-plugin-vue-layouts","pg.asset.manager","app_designer","vue","project","@vitejs/plugin-vue","unplugin-vue-router","@pinegrow/vite-plugin","@vue/devtools","@unocss/preset-icons","unplugin-vue-components","unplugin-auto-import","pg.html"]},"src\\template-resources\\sidemenu-items.vue":{"frameworks":["vue-router","vite-plugin-vue-devtools","vite-plugin-vue-layouts","unplugin-vue-router","unplugin-auto-import","unplugin-vue-components","@unocss/preset-icons","@vue/devtools","@pinegrow/vite-plugin","@vitejs/plugin-vue","vue","app_designer","project","pg.insight.events","pg.vue.tree.painter","pg.css.grid","pg.image.overlay","pg.code-validator","pg.project.items","pg.asset.manager","pg.html"]},"src\\layout\\nav\\sidebar-nav.vue":{"frameworks":["vue-router","pg.insight.events","pg.vue.tree.painter","vite-plugin-vue-devtools","pg.css.grid","pg.image.overlay","vite-plugin-vue-layouts","pg.code-validator","pg.project.items","unplugin-vue-router","pg.asset.manager","app_designer","project","vue","unplugin-auto-import","@vitejs/plugin-vue","@pinegrow/vite-plugin","@vue/devtools","@unocss/preset-icons","unplugin-vue-components","pg.html"]},"src\\pages\\dashboard\\dashboard.vue":{"frameworks":["vue-router","pg.insight.events","pg.vue.tree.painter","vite-plugin-vue-devtools","pg.css.grid","vite-plugin-vue-layouts","pg.image.overlay","unplugin-vue-router","pg.code-validator","pg.project.items","unplugin-auto-import","pg.asset.manager","project","app_designer","unplugin-vue-components","vue","@vitejs/plugin-vue","@unocss/preset-icons","@pinegrow/vite-plugin","@vue/devtools","pg.html"]},"src\\pages\\campaigns\\campaigns-list.vue":{"frameworks":["vue-router","pg.insight.events","pg.vue.tree.painter","vite-plugin-vue-devtools","pg.css.grid","pg.image.overlay","pg.code-validator","vite-plugin-vue-layouts","pg.project.items","pg.asset.manager","app_designer","unplugin-vue-router","project","vue","@vitejs/plugin-vue","@pinegrow/vite-plugin","@vue/devtools","@unocss/preset-icons","unplugin-auto-import","unplugin-vue-components","pg.html"]},"src\\layout\\footer.vue":{"frameworks":["vue-router","pg.insight.events","vite-plugin-vue-devtools","pg.vue.tree.painter","vite-plugin-vue-layouts","unplugin-vue-router","pg.css.grid","unplugin-auto-import","pg.image.overlay","unplugin-vue-components","pg.code-validator","@unocss/preset-icons","project","pg.project.items","@vue/devtools","pg.asset.manager","@pinegrow/vite-plugin","app_designer","@vitejs/plugin-vue","vue","pg.html"]},"src\\layout\\layout-vertical.vue":{"frameworks":["vue-router","pg.insight.events","vite-plugin-vue-devtools","pg.vue.tree.painter","vite-plugin-vue-layouts","unplugin-vue-router","pg.css.grid","unplugin-auto-import","pg.image.overlay","unplugin-vue-components","pg.code-validator","@unocss/preset-icons","project","pg.project.items","@vue/devtools","pg.asset.manager","@pinegrow/vite-plugin","app_designer","@vitejs/plugin-vue","vue","pg.html"]},"src\\layout\\nav\\topbar.vue":{"frameworks":["vue-router","vite-plugin-vue-devtools","vite-plugin-vue-layouts","unplugin-vue-router","unplugin-auto-import","unplugin-vue-components","@unocss/preset-icons","@vue/devtools","@pinegrow/vite-plugin","@vitejs/plugin-vue","vue","app_designer","project","pg.insight.events","pg.vue.tree.painter","pg.css.grid","pg.image.overlay","pg.code-validator","pg.project.items","pg.asset.manager","pg.html"]}},"template_framework_id":"vue","open-pages":["src/App.vue","src/pages/campaigns/campaign-details.vue","src/pages/campaigns/campaigns-list.vue","src/layout/footer.vue","src/layout/guest-layout.vue"],"breakpoints":[],"frameworks":["vue-router","pg.insight.events","vite-plugin-vue-devtools","pg.vue.tree.painter","vite-plugin-vue-layouts","unplugin-vue-router","pg.css.grid","unplugin-auto-import","pg.image.overlay","unplugin-vue-components","pg.code-validator","@unocss/preset-icons","project","pg.project.items","@vue/devtools","pg.asset.manager","@pinegrow/vite-plugin","app_designer","@vitejs/plugin-vue","vue","pg.html"],"urls":{"src/pages/products/column-config.vue":{"open-page-views":[{"w":1024,"h":0}]},"index.html":{"open-page-views":[{"w":1024,"h":0}]},"src/pages/products/products-list.vue":{"open-page-views":[{"w":1024,"h":0}]},"src/App.vue":{"open-page-views":[{"w":1183,"h":0}]},"src/template-resources/sidemenu-items.vue":{"open-page-views":[{"w":1024,"h":0}]},"src/layout/nav/sidebar-nav.vue":{"open-page-views":[{"w":1024,"h":0}]},"src/pages/dashboard/dashboard.vue":{"open-page-views":[{"w":1024,"h":0}]},"src/pages/campaigns/campaigns-list.vue":{"open-page-views":[{"w":1223,"h":0}]},"src/layout/footer.vue":{"open-page-views":[{"w":1024,"h":0}]},"src/layout/layout-vertical.vue":{"open-page-views":[{"w":1024,"h":0}]},"src/layout/nav/topbar.vue":{"open-page-views":[{"w":1024,"h":0}]}},"ai-project-brief":null,"recent-classes":[]}